

{
  "type": "TVEpisode",
  "name": "Dr Seuss' the Lorax",
  "url": "https://www.imdb.com/tt2319314/",
  "poster": "https://m.media-amazon.com/images/M/MV5BMTUzMTk1NjcwMl5BMl5BanBnXkFtZTcwMDI2OTM0OA@@._V1_.jpg",
  "description": "Highlights from the UK Premiere.",
  "review": {
    "author": null,
    "dateCreated": null,
    "inLanguage": null,
    "heading": null,
    "reviewBody": null,
    "reviewRating": {
      "worstRating": null,
      "bestRating": null,
      "ratingValue": null
    }
  },
  "rating": {
    "ratingCount": 12,
    "bestRating": 10,
    "worstRating": 1,
    "ratingValue": 6.1
  },
  "contentRating": null,
  "genre": [
    "Family"
  ],
  "datePublished": "2012-07-24",
  "keywords": null,
  "duration": null,
  "actor": [
    {
      "name": "Johnny Fleming",
      "url": "https://www.imdb.com/name/nm2840083/"
    },
    {
      "name": "Danny DeVito",
      "url": "https://www.imdb.com/name/nm0000362/"
    }
  ],
  "director": [
    {
      "name": "Bob Thomson",
      "url": "https://www.imdb.com/name/nm4311648/"
    }
  ],
  "creator": [
    {
      "name": "Oliver Crocker",
      "url": "https://www.imdb.com/name/nm1211222/"
    }
  ]
}