

{
  "type": "Movie",
  "name": "The Watch",
  "url": "https://www.imdb.com/tt1298649/",
  "poster": "https://m.media-amazon.com/images/M/MV5BMjU5MzI1NTk1MV5BMl5BanBnXkFtZTcwMzk5NzY5Nw@@._V1_.jpg",
  "description": "Four men who form a neighborhood watch group as a way to get out of their day-to-day family routines find themselves defending the Earth from an alien invasion.",
  "contentRating": "15",
  "genre": [
    "Comedy",
    "Sci-Fi"
  ],
  "datePublished": "2012-08-24",
  "keywords": "female full frontal nudity,female frontal nudity,breasts,female nudity,alien",
  "duration": "PT1H42M",
  "rating": {
    "ratingCount": 132523,
    "bestRating": 10,
    "worstRating": 1,
    "ratingValue": 5.7
  },
  "review": {
    "author": "g-hbe",
    "dateCreated": "2022-05-18",
    "inLanguage": "English",
    "heading": "Entertaining, but aimed at teens.",
    "reviewBody": "We found this quite entertaining and the characters were good, but I have to ask who wrote the script - a bunch of schoolboys? Almost every gag was based on d*cks, c*m, big red b*lls, condoms and p*ss. Why? There are plenty of other ways of making gags funny, you know.",
    "reviewRating": {
      "worstRating": 1,
      "bestRating": 10,
      "ratingValue": 7
    }
  },
  "actor": [
    {
      "name": "Ben Stiller",
      "url": "https://www.imdb.com/name/nm0001774/"
    },
    {
      "name": "Vince Vaughn",
      "url": "https://www.imdb.com/name/nm0000681/"
    },
    {
      "name": "Jonah Hill",
      "url": "https://www.imdb.com/name/nm1706767/"
    }
  ],
  "director": [
    {
      "name": "Akiva Schaffer",
      "url": "https://www.imdb.com/name/nm1676223/"
    }
  ],
  "creator": [
    {
      "name": "Jared Stern",
      "url": "https://www.imdb.com/name/nm2972864/"
    },
    {
      "name": "Seth Rogen",
      "url": "https://www.imdb.com/name/nm0736622/"
    },
    {
      "name": "Evan Goldberg",
      "url": "https://www.imdb.com/name/nm1698571/"
    }
  ]
}