{"type": "Movie", "name": "Swimfan", "url": "https://www.imdb.com/tt0283026/", "poster": "https://m.media-amazon.com/images/M/MV5BM2RmZjY1MTItNGM1ZC00NzhlLWI2MjEtYjY1ZjI1M2NiZTg4XkEyXkFqcGdeQXVyMTQxNzMzNDI@._V1_.jpg", "description": null, "contentRating": "12A", "genre": ["Drama", "Thriller"], "datePublished": "2002-09-20", "keywords": "borderline personality disorder,love triangle,fatal attraction,female stalker,sexual obsession", "duration": "PT1H25M", "rating": {"ratingCount": 21096, "bestRating": 10, "worstRating": 1, "ratingValue": 5.1}, "review": {"author": "jillyeung", "dateCreated": "2004-10-15", "inLanguage": "English", "heading": "Young version fatal attraction", "reviewBody": null, "reviewRating": {"worstRating": 1, "bestRating": 10, "ratingValue": 5}}, "actor": [{"name": "Jesse Bradford", "url": "https://www.imdb.com/name/nm0103038/"}, {"name": "Erika Christensen", "url": "https://www.imdb.com/name/nm0159776/"}, {"name": "Shiri Appleby", "url": "https://www.imdb.com/name/nm0032375/"}], "director": [{"name": "John Polson", "url": "https://www.imdb.com/name/nm0689852/"}], "creator": [{"name": "Charles F. Bohl", "url": "https://www.imdb.com/name/nm0092035/"}, {"name": "Phillip Schneider", "url": "https://www.imdb.com/name/nm1152459/"}]}