

{
  "type": "Movie",
  "name": "No Good Deed",
  "url": "https://www.imdb.com/tt2011159/",
  "poster": "https://m.media-amazon.com/images/M/MV5BMzk0OTc3MDM5MF5BMl5BanBnXkFtZTgwOTMzMDMzMjE@._V1_.jpg",
  "description": null,
  "review": {
    "author": "cattjones",
    "dateCreated": "2014-09-12",
    "inLanguage": "English",
    "heading": "Pretty Decent Film",
    "reviewBody": null,
    "reviewRating": {
      "worstRating": 1,
      "bestRating": 10,
      "ratingValue": 7
    }
  },
  "rating": {
    "ratingCount": 21870,
    "bestRating": 10,
    "worstRating": 1,
    "ratingValue": 5.6
  },
  "contentRating": "15",
  "genre": [
    "Crime",
    "Drama",
    "Horror"
  ],
  "datePublished": "2014-11-21",
  "keywords": "psychopath,home invasion,little girl,african american,african american protagonist",
  "duration": "PT1H24M",
  "actor": [
    {
      "name": "Taraji P. Henson",
      "url": "https://www.imdb.com/name/nm0378245/"
    },
    {
      "name": "Idris Elba",
      "url": "https://www.imdb.com/name/nm0252961/"
    },
    {
      "name": "Leslie Bibb",
      "url": "https://www.imdb.com/name/nm0004753/"
    }
  ],
  "director": [
    {
      "name": "Sam Miller",
      "url": "https://www.imdb.com/name/nm0589284/"
    }
  ],
  "creator": [
    {
      "name": "Aimee Lagos",
      "url": "https://www.imdb.com/name/nm1350938/"
    }
  ]
}