

{
  "type": "Movie",
  "name": "Children of Invention",
  "url": "https://www.imdb.com/tt1322282/",
  "poster": "https://m.media-amazon.com/images/M/MV5BMjE5NDg0NDE2MV5BMl5BanBnXkFtZTcwODQzMjMyMg@@._V1_.jpg",
  "description": null,
  "review": {
    "author": "paul_haakonsen",
    "dateCreated": "2019-05-24",
    "inLanguage": "English",
    "heading": "A slow paced but enjoyable movie...",
    "reviewBody": null,
    "reviewRating": {
      "worstRating": 1,
      "bestRating": 10,
      "ratingValue": 6
    }
  },
  "rating": {
    "ratingCount": 661,
    "bestRating": 10,
    "worstRating": 1,
    "ratingValue": 6.5
  },
  "contentRating": "Not Rated",
  "genre": [
    "Drama"
  ],
  "datePublished": "2009-01-18",
  "keywords": "mother,children,young,immigrant,asian woman",
  "duration": "PT1H28M",
  "actor": [
    {
      "name": "Cindy Cheung",
      "url": "https://www.imdb.com/name/nm0156461/"
    },
    {
      "name": "Michael Chen",
      "url": "https://www.imdb.com/name/nm3192506/"
    },
    {
      "name": "Crystal Chiu",
      "url": "https://www.imdb.com/name/nm3191758/"
    }
  ],
  "director": [
    {
      "name": "Tze Chun",
      "url": "https://www.imdb.com/name/nm2309735/"
    }
  ],
  "creator": [
    {
      "name": "Tze Chun",
      "url": "https://www.imdb.com/name/nm2309735/"
    }
  ]
}