{
  "type": "Movie",
  "name": "Kate",
  "url": "https://www.imdb.com/tt7737528/",
  "poster": "https://m.media-amazon.com/images/M/MV5BN2IyYzI4YmQtNzBmMi00Mjg3LWI4NTMtNmZjNjk3YjIwZmJhXkEyXkFqcGdeQXVyMTkxNjUyNQ@@._V1_.jpg",
  "description": "A jaded assassin assigned to target a yakuza clan has 24 hours to find out who poisoned her and get vengeance before she dies.",
  "review": {
    "author": "jackbaumel",
    "dateCreated": "2021-09-11",
    "inLanguage": "English",
    "heading": "This week&apos;s female assassin",
    "reviewBody": "I have a major crush on Winsted. Having said that, good fights, bad cgi car chase. Watchable.",
    "reviewRating": {
      "worstRating": null,
      "bestRating": null,
      "ratingValue": null
    }
  },
  "rating": {
    "ratingCount": 69232,
    "bestRating": 10,
    "worstRating": 1,
    "ratingValue": 6.2
  },
  "contentRating": "15",
  "genre": [
    "Action",
    "Adventure",
    "Crime"
  ],
  "datePublished": "2021-09-10",
  "keywords": "assassin,vengeance,murder,shootout,murderer",
  "duration": "PT1H46M",
  "actor": [
    {
      "name": "Mary Elizabeth Winstead",
      "url": "https://www.imdb.com/name/nm0935541/"
    },
    {
      "name": "Woody Harrelson",
      "url": "https://www.imdb.com/name/nm0000437/"
    },
    {
      "name": "Miku Martineau",
      "url": "https://www.imdb.com/name/nm11008562/"
    }
  ],
  "director": [
    {
      "name": "Cedric Nicolas-Troyan",
      "url": "https://www.imdb.com/name/nm1031639/"
    }
  ],
  "creator": [
    {
      "name": "Umair Aleem",
      "url": "https://www.imdb.com/name/nm7073779/"
    }
  ]
}