{
  "type": "Movie",
  "name": "Freud&apos;s Last Session",
  "url": "https://www.imdb.com/tt20420628/",
  "poster": "https://m.media-amazon.com/images/M/MV5BMGRmODdlZmYtMWFiNC00N2E1LTg5MjUtMWJmMjgyYzJlZjk2XkEyXkFqcGdeQXVyMTQyODg5MjQw._V1_.jpg",
  "description": null,
  "review": {
    "author": "nyccents",
    "dateCreated": "2023-12-25",
    "inLanguage": "English",
    "heading": "Wonderful contemplation of both sides --does God exist?",
    "reviewBody": null,
    "reviewRating": {
      "worstRating": 1,
      "bestRating": 10,
      "ratingValue": 10
    }
  },
  "rating": {
    "ratingCount": 170,
    "bestRating": 10,
    "worstRating": 1,
    "ratingValue": 6.8
  },
  "contentRating": "PG-13",
  "genre": [
    "Drama"
  ],
  "datePublished": "2024-01-12",
  "keywords": "psychology,philosophy,existentialism,sigmund freud character,c.s. lewis character",
  "duration": "PT1H48M",
  "actor": [
    {
      "name": "Anthony Hopkins",
      "url": "https://www.imdb.com/name/nm0000164/"
    },
    {
      "name": "Matthew Goode",
      "url": "https://www.imdb.com/name/nm0328828/"
    },
    {
      "name": "Jodi Balfour",
      "url": "https://www.imdb.com/name/nm3341156/"
    }
  ],
  "director": [
    {
      "name": "Matt Brown",
      "url": "https://www.imdb.com/name/nm0114226/"
    }
  ],
  "creator": [
    {
      "name": "Matt Brown",
      "url": "https://www.imdb.com/name/nm0114226/"
    },
    {
      "name": "Mark St. Germain",
      "url": "https://www.imdb.com/name/nm1059505/"
    }
  ]
}