{
  "type": "Movie",
  "name": "The King&apos;s Man",
  "url": "https://www.imdb.com/tt6856242/",
  "poster": "https://m.media-amazon.com/images/M/MV5BMDEzZDY2ZDktNTlmOS00NThjLThkNTEtMjE5MzI5NWEwZmRjXkEyXkFqcGdeQXVyMDA4NzMyOA@@._V1_.jpg",
  "description": "In the early years of the 20th century, the Kingsman agency is formed to stand against a cabal plotting a war to wipe out millions.",
  "review": {
    "author": "ross91",
    "dateCreated": "2022-02-11",
    "inLanguage": "English",
    "heading": "Terrible",
    "reviewBody": "The story is all over the place! The script is shockingly written, the acting is subpar. I expected a lot more given the 2 previous films, it was a let down. It is a terrible film!",
    "reviewRating": {
      "worstRating": null,
      "bestRating": null,
      "ratingValue": null
    }
  },
  "rating": {
    "ratingCount": 168746,
    "bestRating": 10,
    "worstRating": 1,
    "ratingValue": 6.3
  },
  "contentRating": "15",
  "genre": [
    "Action",
    "Adventure",
    "Thriller"
  ],
  "datePublished": "2021-12-26",
  "keywords": "1910s,third part,based on comic,marvel comics,icon comics",
  "duration": "PT2H11M",
  "actor": [
    {
      "name": "Ralph Fiennes",
      "url": "https://www.imdb.com/name/nm0000146/"
    },
    {
      "name": "Gemma Arterton",
      "url": "https://www.imdb.com/name/nm2605345/"
    },
    {
      "name": "Rhys Ifans",
      "url": "https://www.imdb.com/name/nm0406975/"
    }
  ],
  "director": [
    {
      "name": "Matthew Vaughn",
      "url": "https://www.imdb.com/name/nm0891216/"
    }
  ],
  "creator": [
    {
      "name": "Matthew Vaughn",
      "url": "https://www.imdb.com/name/nm0891216/"
    },
    {
      "name": "Karl Gajdusek",
      "url": "https://www.imdb.com/name/nm2244980/"
    },
    {
      "name": "Mark Millar",
      "url": "https://www.imdb.com/name/nm2092839/"
    }
  ]
}