

{
  "type": "Movie",
  "name": "Lonely Hearts",
  "url": "https://www.imdb.com/tt0441774/",
  "poster": "https://m.media-amazon.com/images/M/MV5BYTIxNGNjZTMtMGM5Ny00MmQ5LWEwODQtYTZkNGY2MjQ1MGM3XkEyXkFqcGdeQXVyNTIzOTk5ODM@._V1_.jpg",
  "description": null,
  "review": {
    "author": "SnoopyStyle",
    "dateCreated": "2015-12-23",
    "inLanguage": "English",
    "heading": "let the killers lead",
    "reviewBody": null,
    "reviewRating": {
      "worstRating": 1,
      "bestRating": 10,
      "ratingValue": 5
    }
  },
  "rating": {
    "ratingCount": 22300,
    "bestRating": 10,
    "worstRating": 1,
    "ratingValue": 6.4
  },
  "contentRating": "15",
  "genre": [
    "Biography",
    "Crime",
    "Drama"
  ],
  "datePublished": "2007-07-27",
  "keywords": "serial killer,criminal investigation,murder investigation,detective,murder",
  "duration": "PT1H48M",
  "actor": [
    {
      "name": "John Travolta",
      "url": "https://www.imdb.com/name/nm0000237/"
    },
    {
      "name": "Salma Hayek",
      "url": "https://www.imdb.com/name/nm0000161/"
    },
    {
      "name": "Jared Leto",
      "url": "https://www.imdb.com/name/nm0001467/"
    }
  ],
  "director": [
    {
      "name": "Todd Robinson",
      "url": "https://www.imdb.com/name/nm0733149/"
    }
  ],
  "creator": [
    {
      "name": "Todd Robinson",
      "url": "https://www.imdb.com/name/nm0733149/"
    }
  ]
}