

{
  "type": "Movie",
  "name": "Jamesy Boy",
  "url": "https://www.imdb.com/tt1673734/",
  "poster": "https://m.media-amazon.com/images/M/MV5BMjM2NjA2NDIzMl5BMl5BanBnXkFtZTgwMTMwOTg1MDE@._V1_.jpg",
  "description": null,
  "contentRating": "Not Rated",
  "genre": [
    "Biography",
    "Crime",
    "Drama"
  ],
  "datePublished": "2014-01-03",
  "keywords": "hooded sweatshirt,cell phone,watching tv,gun pointed at someone&apos;s neck,boot pressed on neck",
  "duration": "PT1H49M",
  "rating": {
    "ratingCount": 6306,
    "bestRating": 10,
    "worstRating": 1,
    "ratingValue": 6.2
  },
  "review": {
    "author": "deelusionalmusic",
    "dateCreated": "2014-01-23",
    "inLanguage": "English",
    "heading": "Diamond in the dirt",
    "reviewBody": null,
    "reviewRating": {
      "worstRating": 1,
      "bestRating": 10,
      "ratingValue": 8
    }
  },
  "actor": [
    {
      "name": "Spencer Rocco Lofranco",
      "url": "https://www.imdb.com/name/nm4901642/"
    },
    {
      "name": "Mary-Louise Parker",
      "url": "https://www.imdb.com/name/nm0000571/"
    },
    {
      "name": "Ving Rhames",
      "url": "https://www.imdb.com/name/nm0000609/"
    }
  ],
  "director": [
    {
      "name": "Trevor White",
      "url": "https://www.imdb.com/name/nm2809465/"
    }
  ],
  "creator": [
    {
      "name": "Lane Shadgett",
      "url": "https://www.imdb.com/name/nm1750295/"
    },
    {
      "name": "Trevor White",
      "url": "https://www.imdb.com/name/nm2809465/"
    }
  ]
}